libreauth/__init__.py
libreauth/oath.py
libreauth/pass.py
libreauth/password.py
libreauth-0.1.0.dev3.data/data/license/LICENSE-EN.txt
libreauth-0.1.0.dev3.data/data/license/LICENSE-FR.txt
libreauth-0.1.0.dev3.dist-info/DESCRIPTION.rst
libreauth-0.1.0.dev3.dist-info/METADATA
libreauth-0.1.0.dev3.dist-info/RECORD
libreauth-0.1.0.dev3.dist-info/WHEEL
libreauth-0.1.0.dev3.dist-info/metadata.json
libreauth-0.1.0.dev3.dist-info/top_level.txt
