Metadata-Version: 2.0
Name: libreauth
Version: 0.1.0.dev3
Summary: Python bindings to the LibreAuth library.
Home-page: https://github.com/breard-r/py-libreauth
Author: Rodolphe Bréard
Author-email: rodolphe@breard.tf
License: CeCILL
Keywords: authentication password oath hotp totp
Platform: UNKNOWN
Classifier: Development Status :: 1 - Planning
Classifier: License :: OSI Approved :: CEA CNRS Inria Logiciel Libre License, version 2.1 (CeCILL-2.1)
Classifier: Programming Language :: Python :: 3.3
Classifier: Programming Language :: Python :: 3.4
Classifier: Programming Language :: Python :: 3.5
Classifier: Programming Language :: Python :: 3.6
Classifier: Programming Language :: Python :: 3.7
Classifier: Programming Language :: Python :: 3 :: Only
Classifier: Programming Language :: Python :: Implementation :: CPython
Classifier: Programming Language :: Python :: Implementation :: PyPy
Classifier: Topic :: Security
Requires-Python: ~=3.3
